{"0": "Blockchain Test", "1": "Rationale Audio", "2": "Anomaly Graph", "3": "Ipfs Test", "4": "Info Cddba", "5": "Test Aes", "6": "Shamir Test", "7": "Test Routes", "8": "Info Cddba", "9": "Test Integration", "10": "Files Cache", "11": "Transaction User", "12": "Package Devdependencies", "13": "Keyshare Routes", "14": "Test Stegochainv", "15": "Api Anomaly", "16": "Test Stegochain", "17": "Info Efc", "18": "Frontend Test", "19": "Package Scripts", "20": "Info Efc", "21": "Deploy Contract", "22": "Messageform Send", "23": "Routes Graph", "24": "Stegochain Sol", "25": "Stegochainv Sol", "26": "Info Efc", "27": "Navbar Receive", "28": "Info Efc", "29": "Info Efc", "30": "Info Efc", "31": "Info Efc", "32": "Deploy Scripts", "33": "Deployv Scripts", "34": "Uploadmedia Guesstype", "35": "Ledgertable Skeletonrow", "36": "Index Pages", "37": "Config Rationale", "38": "Verifycontract Scripts", "39": "Stegochainv Sol", "40": "Stegochain Sol", "41": "Next Config", "42": "App Pages", "43": "Lookup Session", "44": "Config Rationale", "45": "Keyshare Rationale", "46": "Transaction Rationale", "47": "User Rationale", "48": "Modules Init", "49": "Routes Init", "50": "Hardhat Config", "51": "Jest Config", "52": "Postcss Config", "53": "Tailwind Config", "54": "Tests Mocks"}